pycorona/__init__.py
pycorona-0.6.5.dist-info/LICENSE.txt
pycorona-0.6.5.dist-info/METADATA
pycorona-0.6.5.dist-info/WHEEL
pycorona-0.6.5.dist-info/top_level.txt
pycorona-0.6.5.dist-info/RECORD
