Metadata-Version: 2.1
Name: pycorona
Version: 0.6.5
Summary: pycorona is a package to get Coronavirus stats of any country
Home-page: https://github.com/toxicrecker/pycorona
Author: toxicrecker
Author-email: reck.channel.mainlead@gmail.com
License: UNKNOWN
Platform: UNKNOWN
Classifier: Programming Language :: Python :: 3
Classifier: License :: OSI Approved :: MIT License
Classifier: Operating System :: OS Independent
Requires-Python: >=3.6
